{
  "gitSyncId": "678f3593ff64bd2af9b4a4d5_af5928e5-a147-4cb1-a032-8ccbc2c50d5c",
  "unpublishedPage": {
    "layouts": [
      {
        "dsl": {
          "backgroundColor": "none",
          "bottomRow": 380,
          "canExtend": true,
          "containerStyle": "none",
          "detachFromLayout": true,
          "dynamicBindingPathList": [],
          "leftColumn": 0,
          "minHeight": 950,
          "parentColumnSpace": 1,
          "parentRowSpace": 1,
          "rightColumn": 1224,
          "snapColumns": 64,
          "snapRows": 93,
          "topRow": 0,
          "type": "CANVAS_WIDGET",
          "version": 92,
          "widgetId": "0",
          "widgetName": "MainContainer"
        }
      }
    ],
    "name": "Page2 Copy",
    "slug": "page2-copy"
  }
}